{
  "accordion": true,
  "alert": true,
  "alert-dialog": true,
  "aspect-ratio": true,
  "avatar": true,
  "badge": true,
  "breadcrumb": true,
  "button": true,
  "calendar": true,
  "card": true,
  "carousel": true,
  "chart": true,
  "checkbox": true,
  "collapsible": true,
  "command": true,
  "context-menu": true,
  "dialog": true,
  "drawer": true,
  "dropdown-menu": true,
  "hover-card": true,
  "input": true,
  "input-otp": true,
  "label": true,
  "menubar": true,
  "navigation-menu": true,
  "pagination": true,
  "popover": true,
  "progress": true,
  "radio-group": true,
  "resizable": true,
  "scroll-area": true,
  "select": true,
  "separator": true,
  "sheet": true,
  "sidebar": true,
  "skeleton": true,
  "slider": true,
  "sonner": true,
  "switch": true,
  "table": true,
  "tabs": true,
  "textarea": true,
  "toggle": true,
  "toggle-group": true,
  "tooltip": true
}